<data>
    <soft>
        <name>duitangAlbum</name>
        <version>1.2</version>
	<scriptver>1.4</scriptver>
        <downurl>http://yunpan.cn/QkJ8kFPkSIsJS</downurl>
        <downurl2>http://yunpan.cn/QkJ8kvUm4FLk7</downurl2>
	<scripturl>http://www.xcxzq.com/script/duitangAlbum.txt</scripturl>
	<scripturl2>http://www.xcxzq.com/script/duitangAlbum.txt</scripturl2>
        <regurl>http://www.sharebank.com.cn/soft/soft_iframe.php?hide=name&soid=37186</regurl>
        <help>http://www.xcxzq.com/help/duitangAlbum.html</help>
	<bbs>http://www.xcxzq.com</bbs>
      	<news>v3.0版本全新升级内核，建议下载最新版!</news>
<ad>https://svn.code.sf.net/p/xcxzq/code/url/ad.xml</ad>
<mailme>http://mail.qq.com/cgi-bin/qm_share?t=qm_mailme&email=xcxzqcom@163.com</mailme>
<!--
<votes>
s=1,p=104189,
s=1,p=104910,
s=2,p=57829,
</votes>
-->
    </soft>
	<scripts path=".\">
		<script name="duitangAlbum" ver="1.4" file="duitangAlbum.txt">
			<url>http://www.xcxzq.com/script/duitangAlbum.txt</url>
			<url2>https://svn.code.sf.net/p/xcxzq/code/script/duitangAlbum.txt</url2>
		</script>
	</scripts>
</data>
