<data>
    <soft>
        <name>alibabaAlbum</name>
        <version>2.15</version>
        <downurl>http://www.linystar.com/soft/alibabaAlbum/alibabaAlbum.exe</downurl>
        <downurl2>http://www.linystar.com/soft/alibabaAlbum/alibabaAlbum2.exe</downurl2>
        <regurl>http://wpa.qq.com/msgrd?v=3&amp;uin=1329324533&amp;site=qq&amp;menu=yes</regurl>
        <help>http://www.linystar.com/rw/alibabaalbum.html</help>
        <bbs>http://www.linystar.com</bbs>
        <pswd>http://www.linystar.com/logging.php?action=login</pswd>
        <news>新版本修复了一些bug! 更加稳定更加强劲!&#x0D; 强烈建议更新下载！</news>
    </soft>
</data>
