<data>
    <soft>
        <name>flickrAlbum</name>
        <version>2.2</version>
        <downurl>http://l13.yunpan.cn/lk/QkJ8kpJ7dX8ak</downurl>
        <downurl2>http://l13.yunpan.cn/lk/QkJ8vKRX5ZNqy</downurl2>
        <regurl>http://www.sharebank.com.cn/soft/soft_iframe.php?hide=name&soid=40983</regurl>
        <help>http://www.xcxzq.com/help/flickralbum.html</help>
        <bbs>http://www.xcxzq.com</bbs>
      	<news>v2.0全新内核升级，建议更新升级到最新!</news>
<ad>https://svn.code.sf.net/p/xcxzq/code/url/ad.xml</ad>
<mailme>http://mail.qq.com/cgi-bin/qm_share?t=qm_mailme&email=xcxzqcom@163.com</mailme>
<!--
<votes>
s=1,p=112105,
s=2,p=57830,
</votes>
-->
    </soft>
	<scripts path=".\">
		<script name="flickrAlbum" ver="1.3" file="flickrAlbum.txt">
			<url>http://www.xcxzq.com/script/flickrAlbum.txt</url>
			<url2>https://svn.code.sf.net/p/xcxzq/code/script/flickrAlbum.txt</url2>
		</script>
	</scripts>
</data>
